vton_eval/__init__.py
vton_eval/__version__.py
vton_eval/cli/__init__.py
vton_eval/cli/main.py
vton_eval/core/__init__.py
vton_eval/core/config.py
vton_eval/core/data_models.py
vton_eval/core/exceptions.py
vton_eval/core/utils.py
vton_eval/evaluators/__init__.py
vton_eval/evaluators/base.py
vton_eval/evaluators/body_shape.py
vton_eval/evaluators/fit_measurement.py
vton_eval/evaluators/garment_preservation.py
vton_eval/evaluators/identity_preservation.py
vton_eval/models/__init__.py
vton_eval/models/base.py
vton_eval/models/sam_wrapper.py
vton_eval/pipeline/__init__.py
vton_eval/pipeline/orchestrator.py
vton_eval/pipeline/reporter.py
vton_eval/pipeline/scorer.py
vton_eval/vlm/__init__.py
vton_eval/vlm/base.py
vton_eval/vlm/gemini.py
vton_eval-0.1.0.dist-info/LICENSE
vton_eval-0.1.0.dist-info/METADATA
vton_eval-0.1.0.dist-info/WHEEL
vton_eval-0.1.0.dist-info/entry_points.txt
vton_eval-0.1.0.dist-info/RECORD
